{"otherData": {},"traceEvents":[{},{"cat":"function","dur":957,"name":"void __cdecl Engine::OpenGLContext::Init(void)","ph":"X","pid":0,"tid":5032,"ts":528295698567.000},{"cat":"function","dur":6,"name":"void __cdecl Engine::WindowsWindow::SetVSync(bool)","ph":"X","pid":0,"tid":5032,"ts":528295699746.200},{"cat":"function","dur":75241,"name":"void __cdecl Engine::WindowsWindow::Init(const struct Engine::WindowProps &)","ph":"X","pid":0,"tid":5032,"ts":528295624547.500},{"cat":"function","dur":75270,"name":"__cdecl Engine::WindowsWindow::WindowsWindow(const struct Engine::WindowProps &)","ph":"X","pid":0,"tid":5032,"ts":528295624547.300},{"cat":"function","dur":12,"name":"void __cdecl Engine::OpenGLRendererAPI::Init(void)","ph":"X","pid":0,"tid":5032,"ts":528295699850.100},{"cat":"function","dur":5,"name":"__cdecl Engine::OpenGLVertexArray::OpenGLVertexArray(void)","ph":"X","pid":0,"tid":5032,"ts":528295699898.100},{"cat":"function","dur":68,"name":"__cdecl Engine::OpenGLVertexBuffer::OpenGLVertexBuffer(unsigned int)","ph":"X","pid":0,"tid":5032,"ts":528295699949.300},{"cat":"function","dur":0,"name":"void __cdecl Engine::OpenGLVertexBuffer::Bind(void) const","ph":"X","pid":0,"tid":5032,"ts":528295700085.600},{"cat":"function","dur":48,"name":"void __cdecl Engine::OpenGLVertexArray::AddVertexBuffer(const class std::shared_ptr<class Engine::VertexBuffer> &)","ph":"X","pid":0,"tid":5032,"ts":528295700083.200},{"cat":"function","dur":100,"name":"__cdecl Engine::OpenGLIndexBuffer::OpenGLIndexBuffer(unsigned int *,unsigned int)","ph":"X","pid":0,"tid":5032,"ts":528295700486.800},{"cat":"function","dur":1,"name":"void __cdecl Engine::OpenGLIndexBuffer::Bind(void) const","ph":"X","pid":0,"tid":5032,"ts":528295700625.900},{"cat":"function","dur":27,"name":"void __cdecl Engine::OpenGLVertexArray::SetIndexBuffer(const class std::shared_ptr<class Engine::IndexBuffer> &)","ph":"X","pid":0,"tid":5032,"ts":528295700625.400},{"cat":"function","dur":59,"name":"__cdecl Engine::OpenGLTexture2D::OpenGLTexture2D(unsigned int,unsigned int)","ph":"X","pid":0,"tid":5032,"ts":528295700688.400},{"cat":"function","dur":46,"name":"void __cdecl Engine::OpenGLTexture2D::SetData(void *,unsigned int)","ph":"X","pid":0,"tid":5032,"ts":528295700786.700},{"cat":"function","dur":14007,"name":"__cdecl Engine::OpenGLShader::OpenGLShader(const class std::basic_string<char,struct std::char_traits<char>,class std::allocator<char> > &,const class std::basic_string<char,struct std::char_traits<char>,class std::allocator<char> > &,const class std::basic_string<char,struct std::char_traits<char>,class std::allocator<char> > &)","ph":"X","pid":0,"tid":5032,"ts":528295700870.100},{"cat":"function","dur":18,"name":"void __cdecl Engine::OpenGLShader::Use(void) const","ph":"X","pid":0,"tid":5032,"ts":528295714977.000},{"cat":"function","dur":149,"name":"void __cdecl Engine::OpenGLShader::SetInt(const class std::basic_string<char,struct std::char_traits<char>,class std::allocator<char> > &,const int &)","ph":"X","pid":0,"tid":5032,"ts":528295715027.800},{"cat":"function","dur":15355,"name":"void __cdecl Engine::Renderer2D::Init(void)","ph":"X","pid":0,"tid":5032,"ts":528295699892.200},{"cat":"function","dur":15427,"name":"void __cdecl Engine::Renderer::Init(void)","ph":"X","pid":0,"tid":5032,"ts":528295699849.700},{"cat":"function","dur":251,"name":"void __cdecl Engine::ImGuiLayer::OnAttach(void)","ph":"X","pid":0,"tid":5032,"ts":528295715311.600},{"cat":"function","dur":292,"name":"void __cdecl Engine::Application::PushOverLay(class Engine::Layer *)","ph":"X","pid":0,"tid":5032,"ts":528295715309.600},{"cat":"function","dur":91090,"name":"__cdecl Engine::Application::Application(void)","ph":"X","pid":0,"tid":5032,"ts":528295624539.300},{"cat":"function","dur":2,"name":"__cdecl Engine::OrthographicCamera::OrthographicCamera(float,float,float,float)","ph":"X","pid":0,"tid":5032,"ts":528295715663.300},{"cat":"function","dur":230,"name":"__cdecl Engine::OpenGLTexture2D::OpenGLTexture2D(const class std::basic_string<char,struct std::char_traits<char>,class std::allocator<char> > &)","ph":"X","pid":0,"tid":5032,"ts":528295715705.500},{"cat":"function","dur":6470,"name":"__cdecl Engine::OpenGLTexture2D::OpenGLTexture2D(const class std::basic_string<char,struct std::char_traits<char>,class std::allocator<char> > &)","ph":"X","pid":0,"tid":5032,"ts":528295715703.500},{"cat":"function","dur":6588,"name":"void __cdecl App2D::OnAttach(void)","ph":"X","pid":0,"tid":5032,"ts":528295715697.700},{"cat":"function","dur":6626,"name":"void __cdecl Engine::Application::PushLayer(class Engine::Layer *)","ph":"X","pid":0,"tid":5032,"ts":528295715693.600}]}